factories/Impl_factory_swipe_provider.py
factories/__init__.py
factories/impl_factory_git_diff_changes_detector.py
code4swipe-0.1.2.dist-info/METADATA
code4swipe-0.1.2.dist-info/WHEEL
code4swipe-0.1.2.dist-info/entry_points.txt
code4swipe-0.1.2.dist-info/top_level.txt
code4swipe-0.1.2.dist-info/RECORD
