Metadata-Version: 2.4
Name: code4swipe
Version: 0.1.2
Summary: A CLI tool to motivate coding by triggering a 'swipe up' via ADB when new git diff lines are detected.
Home-page: https://github.com/Danand/code4swipe
Author: Andrey Danilov
Author-email: danand@inbox.ru
Classifier: Programming Language :: Python :: 3
Classifier: License :: OSI Approved :: MIT License
Classifier: Operating System :: OS Independent
Requires-Python: >=3.11
Requires-Dist: click
Dynamic: author
Dynamic: author-email
Dynamic: classifier
Dynamic: home-page
Dynamic: requires-dist
Dynamic: requires-python
Dynamic: summary
